opengolfcoach/__init__.py
opengolfcoach/opengolfcoach.cpython-38-aarch64-linux-gnu.so
opengolfcoach-0.1.0.dist-info/METADATA
opengolfcoach-0.1.0.dist-info/WHEEL
opengolfcoach-0.1.0.dist-info/RECORD
