Metadata-Version: 2.4
Name: opengolfcoach
Version: 0.1.0
Classifier: Development Status :: 4 - Beta
Classifier: Intended Audience :: Developers
Classifier: Intended Audience :: Science/Research
Classifier: License :: OSI Approved :: Apache Software License
Classifier: Operating System :: OS Independent
Classifier: Operating System :: MacOS
Classifier: Operating System :: Microsoft :: Windows
Classifier: Operating System :: POSIX :: Linux
Classifier: Programming Language :: Python :: 3
Classifier: Programming Language :: Python :: 3 :: Only
Classifier: Programming Language :: Python :: 3.8
Classifier: Programming Language :: Python :: 3.9
Classifier: Programming Language :: Python :: 3.10
Classifier: Programming Language :: Python :: 3.11
Classifier: Programming Language :: Python :: 3.12
Classifier: Programming Language :: Python :: Implementation :: CPython
Classifier: Programming Language :: Python :: Implementation :: PyPy
Classifier: Programming Language :: Rust
Classifier: Topic :: Scientific/Engineering :: Physics
Classifier: Topic :: Games/Entertainment
Classifier: Typing :: Typed
Requires-Dist: pytest>=7.0 ; extra == 'dev'
Requires-Dist: pytest-cov>=4.0 ; extra == 'dev'
Provides-Extra: dev
Summary: High-performance library for calculating derived golf shot values including trajectory, spin components, and shot classification
Keywords: golf,analytics,ballistics,sports,trajectory,physics,launch-monitor,trackman,flightscope,garmin
Author-email: Open Launch Labs <Support@openlaunch.io>
Maintainer-email: Open Launch Labs <Support@openlaunch.io>
License: Apache-2.0
Requires-Python: >=3.8
Project-URL: Bug Tracker, https://github.com/OpenLaunchLabs/open-golf-coach/issues
Project-URL: Changelog, https://github.com/OpenLaunchLabs/open-golf-coach/blob/main/CHANGELOG.md
Project-URL: Documentation, https://github.com/OpenLaunchLabs/open-golf-coach#readme
Project-URL: Homepage, https://github.com/OpenLaunchLabs/open-golf-coach
Project-URL: Repository, https://github.com/OpenLaunchLabs/open-golf-coach
